LICENSE.rst
README.md
SimpleDiscord.py
setup.py
simple_discord_bot.egg-info/PKG-INFO
simple_discord_bot.egg-info/SOURCES.txt
simple_discord_bot.egg-info/dependency_links.txt
simple_discord_bot.egg-info/requires.txt
simple_discord_bot.egg-info/top_level.txt